hw_package123/__init__.py
hw_package123/hello.py
hw_package123/hello_func.py
hw_package123-1.1.dist-info/LICENSE
hw_package123-1.1.dist-info/METADATA
hw_package123-1.1.dist-info/WHEEL
hw_package123-1.1.dist-info/top_level.txt
hw_package123-1.1.dist-info/RECORD
